setup.py
ore/__init__.py
ore.workflowed.egg-info/PKG-INFO
ore.workflowed.egg-info/SOURCES.txt
ore.workflowed.egg-info/dependency_links.txt
ore.workflowed.egg-info/namespace_packages.txt
ore.workflowed.egg-info/not-zip-safe
ore.workflowed.egg-info/requires.txt
ore.workflowed.egg-info/top_level.txt
ore/workflowed/__init__.py
ore/workflowed/interfaces.py
ore/workflowed/tests.py
ore/workflowed/workflow.py