Metadata-Version: 1.0
Name: ore.workflowed
Version: 0-6-2
Summary: State Machine Workflow Engine
Home-page: http://bitbucket.org/kapilt/oreworkflowed
Author: Kapil Thangavelu
Author-email: kapil.foss@gmail.com
License: ZPL
Keywords: workflow
Platform: UNKNOWN
